protolink/__init__.py
protolink/__version__.py
protolink/agents/__init__.py
protolink/agents/base.py
protolink/agents/builtins/echo_agent.py
protolink/client/__init__.py
protolink/client/agent.py
protolink/client/registry.py
protolink/client/request_spec.py
protolink/context/__init__.py
protolink/core/__init__.py
protolink/core/agent_card.py
protolink/core/artifact.py
protolink/core/context.py
protolink/core/context_manager.py
protolink/core/events.py
protolink/core/message.py
protolink/core/part.py
protolink/core/registry.py
protolink/core/task.py
protolink/core/task_runner.py
protolink/discovery/__init__.py
protolink/discovery/registry.py
protolink/llms/__init__.py
protolink/llms/_deps.py
protolink/llms/base.py
protolink/llms/factory.py
protolink/llms/history.py
protolink/llms/api/__init__.py
protolink/llms/api/anthropic_client.py
protolink/llms/api/base.py
protolink/llms/api/deepseek_client.py
protolink/llms/api/gemini_client.py
protolink/llms/api/hugging_face_client.py
protolink/llms/api/openai_client.py
protolink/llms/prompts/__init__.py
protolink/llms/prompts/agents.py
protolink/llms/prompts/base.py
protolink/llms/prompts/tools.py
protolink/llms/server/__init__.py
protolink/llms/server/base.py
protolink/llms/server/ollama_client.py
protolink/models/__init__.py
protolink/security/__init__.py
protolink/security/auth.py
protolink/security/crypto.py
protolink/server/__init__.py
protolink/server/agent.py
protolink/server/endpoint_handler.py
protolink/server/registry.py
protolink/storage/__init__.py
protolink/storage/base.py
protolink/storage/sqlite.py
protolink/tools/__init__.py
protolink/tools/base.py
protolink/tools/schema.py
protolink/tools/tool.py
protolink/tools/adapters/__init__.py
protolink/tools/adapters/mcp_adapter.py
protolink/transport/__init__.py
protolink/transport/_deps.py
protolink/transport/base.py
protolink/transport/factory.py
protolink/transport/grpc_transport.py
protolink/transport/http_transport.py
protolink/transport/runtime_transport.py
protolink-0.4.6.dist-info/licenses/LICENSE
protolink-0.4.6.dist-info/METADATA
protolink-0.4.6.dist-info/WHEEL
protolink-0.4.6.dist-info/top_level.txt
protolink-0.4.6.dist-info/RECORD
