Metadata-Version: 2.4
Name: protolink
Version: 0.4.6
Summary: A framework for building and managing agents based on the A2A protocol.
Author-email: Nikolaos Maroulis <nikolaos@maroulis.dev>
License-Expression: MIT
Project-URL: Documentation, https://nmaroulis.github.io/protolink/
Project-URL: Repository, https://github.com/nMaroulis/protolink
Requires-Python: >=3.10
License-File: LICENSE
Provides-Extra: http
Requires-Dist: fastapi>=0.128.0; extra == "http"
Requires-Dist: grpcio>=1.76.0; extra == "http"
Requires-Dist: httpx>=0.28.1; extra == "http"
Requires-Dist: pydantic>=2.12.4; extra == "http"
Requires-Dist: starlette>=0.50.0; extra == "http"
Requires-Dist: uvicorn>=0.40.0; extra == "http"
Requires-Dist: websockets>=15.0; extra == "http"
Provides-Extra: llms
Requires-Dist: anthropic>=0.76.0; extra == "llms"
Requires-Dist: huggingface-hub>=1.3.3; extra == "llms"
Requires-Dist: google-genai>=1.60.0; extra == "llms"
Requires-Dist: llama-cpp-python>=0.3.16; extra == "llms"
Requires-Dist: openai>=2.16.0; extra == "llms"
Provides-Extra: mcp
Requires-Dist: mcp>=1.26.0; extra == "mcp"
Provides-Extra: db
Provides-Extra: all
Requires-Dist: protolink[http]; extra == "all"
Requires-Dist: protolink[llms]; extra == "all"
Requires-Dist: protolink[db]; extra == "all"
Provides-Extra: test
Requires-Dist: pytest>=8.3.5; extra == "test"
Requires-Dist: pytest-asyncio>=0.24.0; extra == "test"
Requires-Dist: pytest-cov>=5.0.0; extra == "test"
Requires-Dist: pytest-mock>=3.14.1; extra == "test"
Requires-Dist: ruff==0.14.4; extra == "test"
Requires-Dist: ty>=0.0.14; extra == "test"
Requires-Dist: pre-commit>=4.4.0; extra == "test"
Requires-Dist: protolink[http]; extra == "test"
Provides-Extra: notebook
Requires-Dist: jupyter>=1.1.1; extra == "notebook"
Requires-Dist: notebook>=7.5.3; extra == "notebook"
Provides-Extra: dev
Requires-Dist: protolink[all]; extra == "dev"
Requires-Dist: protolink[test]; extra == "dev"
Requires-Dist: protolink[notebook]; extra == "dev"
Provides-Extra: docs
Requires-Dist: mkdocs>=1.6.1; extra == "docs"
Requires-Dist: mkdocs-material>=9.7.0; extra == "docs"
Provides-Extra: build
Requires-Dist: build>=1.3.0; extra == "build"
Requires-Dist: twine>=6.2.0; extra == "build"
Dynamic: license-file
